simulation/lab1SVSim.sv
module lab1SVSim(
	input 	logic [3:0] s, input logic clk,
	output 	logic [2:0] led, output logic [6:0] seg
);

	xor g1(led[0], s[0], s[1]);
	and g2(led[1], s[2], s[3]);
	
	logic [24:0] counter = 0;
	logic int_osc;
	logic ledOn = 0;
	// Internal high-speed oscillator
	// HSOSC hf_osc (.CLKHFPU(1'b1), .CLKHFEN(1'b1), .CLKHF(int_osc));
	
		// Simple clock divider
	always_ff @(posedge clk)
		begin
			counter <= counter + 1;
			if(counter == 10241637)
				begin
					counter <= 0;
					if(ledOn == 0) ledOn <= 1;
					else ledOn <= 0;
				end
		end
		
	assign led[2] = ledOn;
	
	always_comb begin
		case(s)
			4'h0: seg = 7'b1000000;
			4'h1: seg = 7'b1110011;
			4'h2: seg = 7'b0100100;
			4'h3: seg = 7'b0100001;
			4'h4: seg = 7'b0010011;
			4'h5: seg = 7'b0001001;
			4'h6: seg = 7'b0001000;
			4'h7: seg = 7'b1100011;
			4'h8: seg = 7'b0000000;
			4'h9: seg = 7'b0000001;
			4'ha: seg = 7'b0000010;
			4'hb: seg = 7'b0011000;
			4'hc: seg = 7'b1001100;
			4'hd: seg = 7'b0110000;
			4'he: seg = 7'b0001100;
			4'hf: seg = 7'b0001110;

		endcase
	end

endmodule

`timescale 1ns/1ns
`default_nettype none
`define N_TV 16

module lab1_tb();
 // Set up test signals
 logic clk, reset;
 logic [3:0] s;
 logic [2:0] led, led_expected;
 logic [6:0] seg, seg_expected;
 logic [31:0] vectornum, errors;
 logic [15:0] testvectors[10000:0]; // Vectors of format s[3:0]_seg[6:0]

 // Instantiate the device under test
 lab1SVSim dut(.s(s), .clk(clk), .led(led), .seg(seg));

 // Generate clock signal with a period of 10 timesteps.
 always
   begin
     clk = 1; #5;
     clk = 0; #5;
   end

  
 // At the start of the simulation:
 //  - Load the testvectors
 //  - Pulse the reset line (if applicable)
 initial
   begin
     $readmemb("lab1_testbench.tv", testvectors, 0, `N_TV - 1);
     vectornum = 0; errors = 0;
     reset = 1; #27; reset = 0;
   end
  // Apply test vector on the rising edge of clk
 always @(posedge clk)
   begin
       #1; {s, led_expected, seg_expected} = testvectors[vectornum];
   end
  initial
 begin
   // Create dumpfile for signals
   $dumpfile("lab1_tb.vcd");
   $dumpvars(0, lab1_tb);
 end
  // Check results on the falling edge of clk
 always @(negedge clk)
   begin
     if (~reset) // skip during reset
       begin
         if (led != led_expected || seg != seg_expected)
           begin
             $display("Error: inputs: s=%b",s);
             $display(" outputs: led=%b (%b expected), seg=%b (%b expected)", led, led_expected, seg, seg_expected);
             errors = errors + 1;
           end

      
       vectornum = vectornum + 1;
      
       if (testvectors[vectornum] === 11'bx)
         begin
           $display("%d tests completed with %d errors.", vectornum, errors);
           $finish;
         end
     end
   end
endmodule

simulation/lab1_tb.vcd
$date
	Tue Sep  3 22:13:21 2024
$end
$version
	ModelSim Version 2021.4
$end
$timescale
	1ns
$end

$scope module lab1_tb $end
$var reg 1 ! clk $end
$var reg 1 " reset $end
$var reg 4 # s [3:0] $end
$var reg 3 $ led [2:0] $end
$var reg 3 % led_expected [2:0] $end
$var reg 7 & seg [6:0] $end
$var reg 7 ' seg_expected [6:0] $end
$var reg 32 ( vectornum [31:0] $end
$var reg 32 ) errors [31:0] $end

$scope module dut $end
$var wire 1 * s [3] $end
$var wire 1 + s [2] $end
$var wire 1 , s [1] $end
$var wire 1 - s [0] $end
$var wire 1 . clk $end
$var reg 3 / led [2:0] $end
$var reg 7 0 seg [6:0] $end
$var reg 25 1 counter [24:0] $end
$var reg 1 2 int_osc $end
$var reg 1 3 ledOn $end
$upscope $end
$upscope $end
$enddefinitions $end
#0
$dumpvars
1!
1"
bx #
b0xx $
bx %
bx &
bx '
b0 (
b0 )
b0xx /
bx 0
b1 1
x2
03
x-
x,
x+
x*
1.
$end
#1
b1000000 '
b0 %
b0 #
0-
0,
0+
0*
b0x /
b0 /
b0 $
b1000000 0
b1000000 &
#5
0!
0.
#10
1!
1.
b10 1
#15
0!
0.
#20
1!
1.
b11 1
#25
0!
0.
#27
0"
#30
1!
1.
b100 1
#35
0!
0.
b1 (
#40
1!
1.
b101 1
#41
b1110011 '
b1 %
b1 #
1-
b1 /
b1 $
b1110011 0
b1110011 &
#45
0!
0.
b10 (
#50
1!
1.
b110 1
#51
b100100 '
b10 #
0-
1,
b100100 0
b100100 &
#55
0!
0.
b11 (
#60
1!
1.
b111 1
#61
b100001 '
b0 %
b11 #
1-
b0 /
b0 $
b100001 0
b100001 &
#65
0!
0.
b100 (
#70
1!
1.
b1000 1
#71
b10011 '
b100 #
0-
0,
1+
b10011 0
b10011 &
#75
0!
0.
b101 (
#80
1!
1.
b1001 1
#81
b1001 '
b1 %
b101 #
1-
b1 /
b1 $
b1001 0
b1001 &
#85
0!
0.
b110 (
#90
1!
1.
b1010 1
#91
b1000 '
b110 #
0-
1,
b1000 0
b1000 &
#95
0!
0.
b111 (
#100
1!
1.
b1011 1
#101
b1100011 '
b0 %
b111 #
1-
b0 /
b0 $
b1100011 0
b1100011 &
#105
0!
0.
b1000 (
#110
1!
1.
b1100 1
#111
b0 '
b1000 #
0-
0,
0+
1*
b0 0
b0 &
#115
0!
0.
b1001 (
#120
1!
1.
b1101 1
#121
b1 '
b1 %
b1001 #
1-
b1 /
b1 $
b1 0
b1 &
#125
0!
0.
b1010 (
#130
1!
1.
b1110 1
#131
b10 '
b1010 #
0-
1,
b10 0
b10 &
#135
0!
0.
b1011 (
#140
1!
1.
b1111 1
#141
b11000 '
b0 %
b1011 #
1-
b0 /
b0 $
b11000 0
b11000 &
#145
0!
0.
b1100 (
#150
1!
1.
b10000 1
#151
b1001100 '
b10 %
b1100 #
0-
0,
1+
b10 /
b10 $
b1001100 0
b1001100 &
#155
0!
0.
b1101 (
#160
1!
1.
b10001 1
#161
b110000 '
b11 %
b1101 #
1-
b11 /
b11 $
b110000 0
b110000 &
#165
0!
0.
b1110 (
#170
1!
1.
b10010 1
#171
b1100 '
b1110 #
0-
1,
b1100 0
b1100 &
#175
0!
0.
b1111 (
#180
1!
1.
b10011 1
#181
b1110 '
b10 %
b1111 #
1-
b10 /
b10 $
b1110 0
b1110 &
#185
0!
0.
b10000 (
